sevenseconds/__init__.py
sevenseconds/__main__.py
sevenseconds/cli.py
sevenseconds/config/__init__.py
sevenseconds/config/acm.py
sevenseconds/config/ami.py
sevenseconds/config/bastion.py
sevenseconds/config/cloudtrail.py
sevenseconds/config/cloudwatch.py
sevenseconds/config/configure.py
sevenseconds/config/ec2.py
sevenseconds/config/elasticache.py
sevenseconds/config/iam.py
sevenseconds/config/kms.py
sevenseconds/config/policysimulator.py
sevenseconds/config/rds.py
sevenseconds/config/route53.py
sevenseconds/config/s3.py
sevenseconds/config/securitygroup.py
sevenseconds/config/vpc.py
sevenseconds/helper/__init__.py
sevenseconds/helper/auth.py
sevenseconds/helper/aws.py
sevenseconds/helper/network.py
sevenseconds/helper/regioninfo.py
stups_sevenseconds-1.2.112.dist-info/DESCRIPTION.rst
stups_sevenseconds-1.2.112.dist-info/METADATA
stups_sevenseconds-1.2.112.dist-info/RECORD
stups_sevenseconds-1.2.112.dist-info/WHEEL
stups_sevenseconds-1.2.112.dist-info/entry_points.txt
stups_sevenseconds-1.2.112.dist-info/metadata.json
stups_sevenseconds-1.2.112.dist-info/top_level.txt
