Metadata-Version: 2.0
Name: stups-sevenseconds
Version: 1.2.112
Summary: Configure AWS accounts
Home-page: https://github.com/zalando-stups/sevenseconds
Author: Henning Jacobs
Author-email: henning.jacobs@zalando.de
License: Apache License 2.0
Keywords: aws account vpc
Platform: UNKNOWN
Classifier: Development Status :: 4 - Beta
Classifier: Environment :: Console
Classifier: Intended Audience :: Developers
Classifier: Intended Audience :: System Administrators
Classifier: License :: OSI Approved :: Apache Software License
Classifier: Operating System :: POSIX :: Linux
Classifier: Programming Language :: Python
Classifier: Programming Language :: Python :: 3.4
Classifier: Programming Language :: Python :: Implementation :: CPython
License-File: LICENSE
Requires-Dist: clickclick (>=1.2.1)
Requires-Dist: boto3 (>=1.9.212)
Requires-Dist: botocore (>=1.5.26)
Requires-Dist: netaddr (>=0.7.18)
Requires-Dist: requests (>=2.9.1)
Requires-Dist: keyring
Requires-Dist: python-gnupg (>=0.3.7)
Requires-Dist: python-dateutil
Requires-Dist: datetime
Requires-Dist: PyYAML
Requires-Dist: PyJWT (<3.0,>=2.0)
Requires-Dist: stups-zign (>=1.1.26)
Requires-Dist: setuptools (>=30)
Requires-Dist: flake8
